CHANGES
LICENSE
MANIFEST.in
README
setup.py
sanction/__init__.py
sanction/client.py
sanction/test.py
sanction.egg-info/PKG-INFO
sanction.egg-info/SOURCES.txt
sanction.egg-info/dependency_links.txt
sanction.egg-info/top_level.txt