Metadata-Version: 1.1
Name: sanction
Version: 0.4
Summary: A simple, lightweight OAuth2 client
Home-page: https://github.com/demianbrecht/sanction
Author: Demian Brecht
Author-email: demianbrecht@gmail.com
License: UNKNOWN
Keywords: python,oauth2
Platform: UNKNOWN
Classifier: Development Status :: 5 - Production/Stable
Classifier: Environment :: Web Environment
Classifier: Intended Audience :: Developers
Classifier: License :: OSI Approved :: MIT License
Classifier: Natural Language :: English
Classifier: Programming Language :: Python
Classifier: Topic :: Internet :: WWW/HTTP
Classifier: Topic :: Internet :: WWW/HTTP :: Site Management
Classifier: Topic :: Software Development :: Libraries :: Python Modules
Classifier: Topic :: System :: Systems Administration :: Authentication/Directory
